sso_client_manager/__init__.py
sso_client_manager/apps.py
sso_client_manager/middlewares.py
sso_client_manager/urls.py
sso_client_manager/views.py
django_sso_client_manager-0.0.7.dist-info/METADATA
django_sso_client_manager-0.0.7.dist-info/WHEEL
django_sso_client_manager-0.0.7.dist-info/top_level.txt
django_sso_client_manager-0.0.7.dist-info/RECORD
