Metadata-Version: 2.1
Name: django-sso-client-manager
Version: 0.0.7
Summary: Django-SSO-Client-Manager is a Django application designed to simplify the management of Single Sign-On (SSO) clients within a web application. It provides functionalities for handling login and logout processes and conveniently sets codes in cookies for seamless authentication and user session management. By integrating this app into a Django project, developers can streamline the implementation of SSO functionality and enhance the overall user experience.
Home-page: https://github.com/rjnp2/django-sso-client-manager
Author: rjnp2
Author-email: rjnp2@outlook.com
License: MIT License
Platform: UNKNOWN
Classifier: Environment :: Web Environment
Classifier: Framework :: Django
Classifier: Intended Audience :: Developers
Classifier: License :: OSI Approved :: MIT License
Classifier: Operating System :: OS Independent
Classifier: Programming Language :: Python
Classifier: Programming Language :: Python :: 3.8
Classifier: Topic :: Internet :: WWW/HTTP
Classifier: Topic :: Internet :: WWW/HTTP :: Dynamic Content
Requires-Python: >=3.8
Requires-Dist: requests (>=2.28.1)
Provides-Extra: dev
Requires-Dist: twine (>=4.0.2) ; extra == 'dev'
